calcmass/__init__.py
calcmass/__main__.py
calcmass/mass.py
calcmass/pt_data.py
calcmass-2.0.dist-info/LICENSE.txt
calcmass-2.0.dist-info/METADATA
calcmass-2.0.dist-info/WHEEL
calcmass-2.0.dist-info/entry_points.txt
calcmass-2.0.dist-info/top_level.txt
calcmass-2.0.dist-info/RECORD
