Metadata-Version: 2.1
Name: calcmass
Version: 2.0
Summary: A script to calculate the molecular mass of a chemical compound in g/mol with its chemical formula
Home-page: https://github.com/konman2/Mass
Author: Manu Kondapaneni
Author-email: manukonda11@gmail.com
License: UNKNOWN
Download-URL: https://github.com/konman2/Mass/archive/2.0.tar.gz
Keywords: mass,chemical,compound,chemistry,element,calculator
Platform: UNKNOWN
Requires-Dist: argparse
